newversion/__init__.py
newversion/__main__.py
newversion/cli_parser.py
newversion/constants.py
newversion/eol_fixer.py
newversion/exceptions.py
newversion/executor.py
newversion/logger.py
newversion/main.py
newversion/package_version.py
newversion/py.typed
newversion/type_defs.py
newversion/utils.py
newversion/version.py
newversion-3.1.0.dist-info/LICENSE
newversion-3.1.0.dist-info/METADATA
newversion-3.1.0.dist-info/WHEEL
newversion-3.1.0.dist-info/entry_points.txt
newversion-3.1.0.dist-info/top_level.txt
newversion-3.1.0.dist-info/RECORD
