Metadata-Version: 2.1
Name: newversion
Version: 3.1.0
Summary: PEP 440 version manager
Author-email: Vlad Emelianov <vlad.emelianov.nz@gmail.com>
License: MIT License
Project-URL: Documentation, https://newversion.readthedocs.io/en/latest/
Project-URL: Repository, https://github.com/vemel/newversion
Project-URL: Issues, https://github.com/vemel/newversion/issues
Keywords: version,pep440
Classifier: Development Status :: 5 - Production/Stable
Classifier: Environment :: Console
Classifier: License :: OSI Approved :: MIT License
Classifier: Natural Language :: English
Classifier: Operating System :: OS Independent
Classifier: Programming Language :: Python :: 3
Classifier: Programming Language :: Python :: 3.8
Classifier: Programming Language :: Python :: 3.9
Classifier: Programming Language :: Python :: 3.10
Classifier: Programming Language :: Python :: 3.11
Classifier: Programming Language :: Python :: 3.12
Classifier: Programming Language :: Python :: 3.13
Classifier: Programming Language :: Python :: 3.14
Classifier: Programming Language :: Python :: 3 :: Only
Classifier: Programming Language :: Python :: Implementation :: CPython
Classifier: Typing :: Typed
Classifier: Topic :: Software Development :: Libraries :: Python Modules
Requires-Python: >=3.9
License-File: LICENSE
Requires-Dist: packaging >=20.0
Requires-Dist: typing-extensions >=4.1.0
Provides-Extra: build
Requires-Dist: setuptools ; extra == 'build'
